{
  "what-is-fractions": "Что такое дроби",
  "main-property": "Основное свойство дроби",
  "proper-improper": "Правильная, неправильная и составная дробь",
  "addition-substraction": "Складывание и вычитание дробей с одинаковым знаменателем",
  "common-denominator": "Общий знаменатель для дробей",
  "comparison": "Сравнение дробей",
  "addition-substraction-diff-denominator": "Складываем и вычитаем дроби с разным знаменателем",
  "multiplication-proper": "Умножение правильных дробей",
  "division-proper": "Деление правильных дробей",
  "multiplication-division-compound": "Умножение и деление составных дробей",
  "exercises": "Текстовые задачи с дробями"
}
